model_admin/__init__.py
model_admin/apps.py
model_admin/hooks/__init__.py
model_admin/hooks/buttons/__init__.py
model_admin/hooks/buttons/components/__init__.py
model_admin/hooks/buttons/components/add.py
model_admin/hooks/buttons/components/base.py
model_admin/hooks/buttons/components/delete.py
model_admin/hooks/buttons/components/duplicate.py
model_admin/hooks/buttons/components/edit.py
model_admin/hooks/buttons/components/inspect.py
model_admin/hooks/buttons/entity/__init__.py
model_admin/hooks/buttons/entity/button.py
model_admin/hooks/buttons/helpers/__init__.py
model_admin/hooks/buttons/helpers/base.py
model_admin/hooks/buttons/helpers/default.py
model_admin/hooks/modeladmin/__init__.py
model_admin/hooks/modeladmin/options.py
model_admin/hooks/views/__init__.py
model_admin/hooks/views/duplicate.py
model_admin/templates/modeladmin/duplicate.html
model_admin/tests/__init__.py
model_admin/tests/hooks/__init__.py
model_admin/tests/hooks/buttons/__init__.py
model_admin/tests/hooks/buttons/components/__init__.py
model_admin/tests/hooks/buttons/components/test_delete.py
model_admin/tests/hooks/buttons/helpers/__init__.py
model_admin/tests/hooks/buttons/helpers/test_base.py
model_admin/tests/hooks/buttons/test_base/__init__.py
model_admin/tests/hooks/buttons/test_base/base.py
model_admin/tests/hooks/buttons/test_base/mocks.py
model_admin/tests/utils/__init__.py
model_admin/tests/utils/test_duplicate.py
model_admin/utils/__init__.py
model_admin/utils/duplicate.py
wagtail_modeladmin_buttons-1.0.5.dist-info/LICENSE
wagtail_modeladmin_buttons-1.0.5.dist-info/METADATA
wagtail_modeladmin_buttons-1.0.5.dist-info/WHEEL
wagtail_modeladmin_buttons-1.0.5.dist-info/top_level.txt
wagtail_modeladmin_buttons-1.0.5.dist-info/RECORD
